vbcore/__init__.py
vbcore/__main__.py
vbcore/aio.py
vbcore/base.py
vbcore/batch.py
vbcore/configurator.py
vbcore/context.py
vbcore/csvfile.py
vbcore/date_helper.py
vbcore/dispatcher.py
vbcore/enums.py
vbcore/exceptions.py
vbcore/factory.py
vbcore/files.py
vbcore/heartbeat.py
vbcore/importer.py
vbcore/json.py
vbcore/lambdas.py
vbcore/loggers.py
vbcore/misc.py
vbcore/py.typed
vbcore/system.py
vbcore/types.py
vbcore/version.py
vbcore/yaml.py
vbcore/brokers/__init__.py
vbcore/brokers/base.py
vbcore/brokers/consumer.py
vbcore/brokers/data.py
vbcore/brokers/dummy.py
vbcore/brokers/factory.py
vbcore/brokers/nats.py
vbcore/brokers/publisher.py
vbcore/crypto/__init__.py
vbcore/crypto/argon.py
vbcore/crypto/base.py
vbcore/crypto/bcrypt.py
vbcore/crypto/exceptions.py
vbcore/crypto/factory.py
vbcore/crypto/hashes.py
vbcore/data/__init__.py
vbcore/data/transformations/__init__.py
vbcore/data/transformations/builders/__init__.py
vbcore/data/transformations/builders/base.py
vbcore/data/transformations/builders/csv.py
vbcore/data/transformations/builders/dicttoxml.py
vbcore/data/transformations/builders/factory.py
vbcore/data/transformations/builders/html.py
vbcore/data/transformations/builders/json.py
vbcore/data/transformations/builders/xml.py
vbcore/data/transformations/builders/yaml.py
vbcore/datastruct/__init__.py
vbcore/datastruct/buffer.py
vbcore/datastruct/cache.py
vbcore/datastruct/dictionaries.py
vbcore/datastruct/lazy.py
vbcore/datastruct/misc.py
vbcore/datastruct/orderer_set.py
vbcore/db/__init__.py
vbcore/db/base.py
vbcore/db/events.py
vbcore/db/exceptions.py
vbcore/db/listener.py
vbcore/db/mixins.py
vbcore/db/mysql_dumper.py
vbcore/db/repo.py
vbcore/db/schema.py
vbcore/db/sqla.py
vbcore/db/support.py
vbcore/db/types.py
vbcore/db/views.py
vbcore/db/schema_display/__init__.py
vbcore/db/schema_display/db_diagram.py
vbcore/db/schema_display/model_diagram.py
vbcore/dictutils/__init__.py
vbcore/dictutils/flatter_dict.py
vbcore/dictutils/misc.py
vbcore/excel/__init__.py
vbcore-2.3.1.dist-info/METADATA
vbcore-2.3.1.dist-info/WHEEL
vbcore-2.3.1.dist-info/entry_points.txt
vbcore-2.3.1.dist-info/top_level.txt
vbcore-2.3.1.dist-info/RECORD
